upy_error/__init__.py
upy_error/base.py
upy_error/config.py
upy_error-0.0.3.dist-info/METADATA
upy_error-0.0.3.dist-info/WHEEL
upy_error-0.0.3.dist-info/top_level.txt
upy_error-0.0.3.dist-info/RECORD
